listio
