Metadata-Version: 1.1
Name: listio
Version: 1.1.0
Summary: Read/write lists and maps (two dimensional lists) from/to files.
Home-page: https://github.com/jakubvalenta/listio
Author: Jakub Valenta
Author-email: jakub@jakubvalenta.cz
License: Apache Software License
Platform: UNKNOWN
Classifier: Development Status :: 3 - Alpha
Classifier: Intended Audience :: Developers
Classifier: License :: OSI Approved :: Apache Software License
Classifier: Topic :: Software Development
Classifier: Programming Language :: Python :: 2.7
Classifier: Programming Language :: Python :: 3
Classifier: Programming Language :: Python :: 3.4
Classifier: Programming Language :: Python :: 3.5
Classifier: Programming Language :: Python :: 3.6
